README.md
setup.py
laizy/__init__.py
laizy/data_analysis.py
laizy/pd_tools.py
laizy/text_tools.py
laizy.egg-info/PKG-INFO
laizy.egg-info/SOURCES.txt
laizy.egg-info/dependency_links.txt
laizy.egg-info/requires.txt
laizy.egg-info/top_level.txt